{
  "indexes": [
    {
      "collectionGroup": "transactions",
      "queryScope": "COLLECTION",
      "fields": [
        { "fieldPath": "society_id", "order": "ASCENDING" },
        { "fieldPath": "type", "order": "ASCENDING" }
      ]
    },
    {
      "collectionGroup": "issues",
      "queryScope": "COLLECTION",
      "fields": [
        { "fieldPath": "society_id", "order": "ASCENDING" },
        { "fieldPath": "createdAt", "order": "DESCENDING" }
      ]
    }
  ],
  "fieldOverrides": []
}
